phonexia_referential_deepfake_detection_client.py
phonexia_referential_deepfake_detection_client-1.0.0.dist-info/METADATA
phonexia_referential_deepfake_detection_client-1.0.0.dist-info/WHEEL
phonexia_referential_deepfake_detection_client-1.0.0.dist-info/entry_points.txt
phonexia_referential_deepfake_detection_client-1.0.0.dist-info/RECORD
